comtraderecord/ComtradeParser.py
comtraderecord/__init__.py
comtraderecord/_version.py
comtraderecord/comtradeWriter.py
comtraderecord/pyComtrade.py
comtraderecord/pyRelayAlg.py
comtraderecord-1.0.2.data/data/requirements.txt
comtraderecord-1.0.2.dist-info/METADATA
comtraderecord-1.0.2.dist-info/WHEEL
comtraderecord-1.0.2.dist-info/top_level.txt
comtraderecord-1.0.2.dist-info/RECORD
