Metadata-Version: 2.1
Name: comtraderecord
Version: 1.0.2
Summary: Read/Write comtrade recording, commonly used algorithm for recording.
Home-page: https://pypi.org/project/comtraderecord/
Author: haitao
Author-email: haitao.lian@siemens.com
Classifier: Programming Language :: Python :: 3
Classifier: License :: OSI Approved :: MIT License
Classifier: Operating System :: OS Independent
Requires-Python: >=3.6
Requires-Dist: numpy>=1.10.1
